tursi/__init__.py
tursi/engine.py
tursi/test.py
tursi-0.2.1.dist-info/licenses/LICENSE
tursi-0.2.1.dist-info/METADATA
tursi-0.2.1.dist-info/WHEEL
tursi-0.2.1.dist-info/entry_points.txt
tursi-0.2.1.dist-info/top_level.txt
tursi-0.2.1.dist-info/RECORD
