Metadata-Version: 2.4
Name: tursi
Version: 0.2.1
Summary: A simple framework to deploy AI models locally with one command, no containers needed
Home-page: https://github.com/BlueTursi/tursi-ai
Author: Kresna Sucandra
Author-email: kresnasucandra@gmail.com
License: MIT
Classifier: Programming Language :: Python :: 3
Classifier: License :: OSI Approved :: MIT License
Classifier: Operating System :: OS Independent
Requires-Python: >=3.8
License-File: LICENSE
Requires-Dist: transformers
Requires-Dist: flask
Requires-Dist: torch>=2.3.2
Requires-Dist: requests
Requires-Dist: numpy<2
Requires-Dist: python-dotenv
Requires-Dist: cryptography
Requires-Dist: Flask-Limiter>=3.5.0
Dynamic: author
Dynamic: author-email
Dynamic: classifier
Dynamic: description
Dynamic: description-content-type
Dynamic: home-page
Dynamic: license
Dynamic: license-file
Dynamic: requires-dist
Dynamic: requires-python
Dynamic: summary
